{
  "gitSyncId": "68bfdef5535e0121b9d08747_02b9ffe3-ee2f-49eb-8b60-e9529a67edb8",
  "id": "Chat Widget_chat.lastUserMessage",
  "pluginId": "js-plugin",
  "pluginType": "JS",
  "unpublishedAction": {
    "actionConfiguration": {
      "encodeParamsToggle": true,
      "jsArguments": [],
      "paginationType": "NONE",
      "timeoutInMillisecond": 10000
    },
    "collectionId": "Chat Widget_chat",
    "confirmBeforeExecute": false,
    "datasource": {
      "isAutoGenerated": false,
      "name": "UNUSED_DATASOURCE",
      "pluginId": "js-plugin"
    },
    "dynamicBindingPathList": [
      {
        "key": "body"
      }
    ],
    "fullyQualifiedName": "chat.lastUserMessage",
    "name": "lastUserMessage",
    "pageId": "Chat Widget",
    "runBehaviour": "MANUAL",
    "userSetOnLoad": false
  }
}